giftbit/__init__.py
giftbit/exceptions.py
giftbit/giftbit.py
giftbit-0.1.dist-info/METADATA
giftbit-0.1.dist-info/RECORD
giftbit-0.1.dist-info/WHEEL
giftbit-0.1.dist-info/top_level.txt
tests/__init__.py
tests/test_giftbit.py
