Metadata-Version: 2.1
Name: giftbit
Version: 0.1
Summary: A Python SDK for GiftBit's API
Home-page: https://github.com/jaydenwindle/giftbit-python
Author: Jayden Windle
Author-email: jaydenwindle@gmail.com
License: UNKNOWN
Download-URL: https://github.com/jaydenwindle/giftbit-python/archive/0.1.tar.gz
Platform: UNKNOWN
